odoo9_addon_invoice_comment_template-9.0.1.0.0-py2.7-nspkg.pth
odoo_addons/invoice_comment_template/__openerp__.py
odoo_addons/invoice_comment_template/account_invoice.py
odoo_addons/invoice_comment_template/__init__.py
odoo_addons/invoice_comment_template/README.rst
odoo_addons/invoice_comment_template/security/ir.model.access.csv
odoo_addons/invoice_comment_template/i18n/fr.po
odoo_addons/invoice_comment_template/i18n/invoice_comment_template.pot
odoo_addons/invoice_comment_template/views/report_invoice.xml
odoo_addons/invoice_comment_template/views/account_invoice.xml
odoo_addons/invoice_comment_template/views/base_comment_template.xml
odoo9_addon_invoice_comment_template-9.0.1.0.0.dist-info/top_level.txt
odoo9_addon_invoice_comment_template-9.0.1.0.0.dist-info/WHEEL
odoo9_addon_invoice_comment_template-9.0.1.0.0.dist-info/RECORD
odoo9_addon_invoice_comment_template-9.0.1.0.0.dist-info/metadata.json
odoo9_addon_invoice_comment_template-9.0.1.0.0.dist-info/DESCRIPTION.rst
odoo9_addon_invoice_comment_template-9.0.1.0.0.dist-info/METADATA
odoo9_addon_invoice_comment_template-9.0.1.0.0.dist-info/namespace_packages.txt
